{
    "POP_DOMAINE": {
        "type": "String"
    },
    "POP_COORDINATES_POINT": {
        "type": "Point"
    },
    "POP_COORDINATES_POLYGON": {
        "type": "GeoJson"
    },
    "POP_HAS_IMAGE": {
        "type": "Array"
    },
    "POP_HAS_LOCATION": {
        "type": "Array"
    },
    "POP_DATE": {
        "type": "Array"
    },
    "REF": {
        "type": "String"
    },
    "TOUT": {
        "type": "String"
    },
    "ACTU": {
        "type": "String"
    },
    "ADRS": {
        "type": "String"
    },
    "AFFE": {
        "type": "String"
    },
    "AIRE": {
        "type": "String"
    },
    "APRO": {
        "type": "Array"
    },
    "ARCHEO": {
        "type": "String"
    },
    "AUTP": {
        "type": "Array"
    },
    "AUTR": {
        "type": "Array"
    },
    "CADA": {
        "type": "Array"
    },
    "CANT": {
        "type": "String"
    },
    "COLL": {
        "type": "Array"
    },
    "COM": {
        "type": "String"
    },
    "COOR": {
        "type": "String"
    },
    "COORM": {
        "type": "String"
    },
    "COPY": {
        "type": "String"
    },
    "COUV": {
        "type": "Array"
    },
    "DATE": {
        "type": "Array"
    },
    "DBOR": {
        "type": "String"
    },
    "DOMN": {
        "type": "Array"
    },
    "DENO": {
        "type": "Array"
    },
    "DENQ": {
        "type": "String"
    },
    "DEPL": {
        "type": "String"
    },
    "DESC": {
        "type": "String"
    },
    "DIMS": {
        "type": "String"
    },
    "DOSS": {
        "type": "String"
    },
    "DPRO": {
        "type": "String"
    },
    "DPT": {
        "type": "String"
    },
    "EDIF": {
        "type": "String"
    },
    "ELEV": {
        "type": "Array"
    },
    "ENER": {
        "type": "Array"
    },
    "ESCA": {
        "type": "Array"
    },
    "ETAG": {
        "type": "Array"
    },
    "ETAT": {
        "type": "String"
    },
    "ETUD": {
        "type": "String"
    },
    "GENR": {
        "type": "String"
    },
    "HIST": {
        "type": "String"
    },
    "HYDR": {
        "type": "String"
    },
    "IMPL": {
        "type": "Array"
    },
    "INSEE": {
        "type": "String"
    },
    "INTE": {
        "type": "Array"
    },
    "JATT": {
        "type": "Array"
    },
    "JDAT": {
        "type": "Array"
    },
    "LBASE2": {
        "type": "String"
    },
    "LIEU": {
        "type": "String"
    },
    "LOCA": {
        "type": "String"
    },
    "MFICH": {
        "type": "String"
    },
    "MOSA": {
        "type": "String"
    },
    "MHPP": {
        "type": "String"
    },
    "MICR": {
        "type": "String"
    },
    "MURS": {
        "type": "Array"
    },
    "NBOR": {
        "type": "String"
    },
    "NOMS": {
        "type": "Array"
    },
    "OBS": {
        "type": "String"
    },
    "PAFF": {
        "type": "String"
    },
    "PART": {
        "type": "Array"
    },
    "PARN": {
        "type": "Array"
    },
    "PDEN": {
        "type": "String"
    },
    "PERS": {
        "type": "Array"
    },
    "PLAN": {
        "type": "String"
    },
    "PLOC": {
        "type": "String"
    },
    "PPRO": {
        "type": "String"
    },
    "PREP": {
        "type": "Array"
    },
    "PROT": {
        "type": "Array"
    },
    "PSTA": {
        "type": "String"
    },
    "REFE": {
        "type": "Array"
    },
    "REFO": {
        "type": "Array"
    },
    "REFP": {
        "type": "Array"
    },
    "REG": {
        "type": "String"
    },
    "REMA": {
        "type": "String"
    },
    "REMP": {
        "type": "String"
    },
    "RENV": {
        "type": "Array"
    },
    "REPR": {
        "type": "Array"
    },
    "RFPA": {
        "type": "String"
    },
    "SCLD": {
        "type": "Array"
    },
    "SCLE": {
        "type": "Array"
    },
    "SCLX": {
        "type": "Array"
    },
    "SITE": {
        "type": "String"
    },
    "STAT": {
        "type": "Array"
    },
    "TECH": {
        "type": "Array"
    },
    "TICO": {
        "type": "String"
    },
    "TOIT": {
        "type": "Array"
    },
    "TYPO": {
        "type": "Array"
    },
    "VERT": {
        "type": "String"
    },
    "REFIM": {
        "type": "String"
    },
    "IMG": {
        "type": "String"
    },
    "VIDEO": {
        "type": "String"
    },
    "DOSURL": {
        "type": "String"
    },
    "DOSURLP": {
        "type": "String"
    },
    "DOSADRS": {
        "type": "String"
    },
    "LIENS": {
        "type": "Array"
    },
    "IMAGE": {
        "type": "String"
    },
    "VISI": {
        "type": "Array"
    },
    "VOCA": {
        "type": "String"
    },
    "VOUT": {
        "type": "Array"
    },
    "WEB": {
        "type": "String"
    },
    "ZONE": {
        "type": "String"
    },
    "THEM": {
        "type": "String"
    },
    "ACMH": {
        "type": "String"
    },
    "ACURL": {
        "type": "String"
    },
    "WADRS": {
        "type": "String"
    },
    "WCOM": {
        "type": "String"
    },
    "WRENV": {
        "type": "String"
    },
    "REFM": {
        "type": "String"
    },
    "CONTACT": {
        "type": "String"
    },
    "IDAGR": {
        "type": "String"
    },
    "LMDP": {
        "type": "String"
    },
    "PINT": {
        "type": "String"
    },
    "DLAB": {
        "type": "String"
    },
    "APPL": {
        "type": "String"
    }
}